entex/__init__.py
entex/metrices.py
entex/optimizator.py
entex/text_preprocessor.py
entex-1.0.0.dist-info/LICENSE
entex-1.0.0.dist-info/METADATA
entex-1.0.0.dist-info/WHEEL
entex-1.0.0.dist-info/top_level.txt
entex-1.0.0.dist-info/RECORD
